propgraph.py
propgraph-0.1.1.dist-info/METADATA
propgraph-0.1.1.dist-info/WHEEL
propgraph-0.1.1.dist-info/licenses/LICENSE
propgraph-0.1.1.dist-info/RECORD
