Metadata-Version: 2.1
Name: propgraph
Version: 0.1.1
Summary: A graph structure that can take arbitrary properties.
Author: Rob Reid
License-File: LICENSE
Keywords: data,graph,structure
